setup.py
math_dist_ig/Binomialdistribution.py
math_dist_ig/Gaussiandistribution.py
math_dist_ig/Generaldistribution.py
math_dist_ig/__init__.py
math_dist_ig.egg-info/PKG-INFO
math_dist_ig.egg-info/SOURCES.txt
math_dist_ig.egg-info/dependency_links.txt
math_dist_ig.egg-info/not-zip-safe
math_dist_ig.egg-info/top_level.txt