Metadata-Version: 1.0
Name: math-dist-ig
Version: 0.1
Summary: Gaussian and binomial distributions
Home-page: UNKNOWN
Author: Igor Tunde
Author-email: igortunde@yahoo.com
License: UNKNOWN
Platform: UNKNOWN
